invicta/_version.py
invicta/arguments.py
invicta/cipher.py
invicta/english.py
invicta/main.py
invicta/output.py
invicta/tests/test_can_caesar_encrypt.py
invicta/tests/test_decrypt.py
invicta/tests/test_encrypt.py
invicta/tests/test_english.py
invicta-0.6.1.dist-info/LICENSE
invicta-0.6.1.dist-info/METADATA
invicta-0.6.1.dist-info/WHEEL
invicta-0.6.1.dist-info/entry_points.txt
invicta-0.6.1.dist-info/top_level.txt
invicta-0.6.1.dist-info/RECORD
