Metadata-Version: 2.1
Name: invicta
Version: 0.6.1
Author: Lily Patchen
License: MIT License
Keywords: encryption,cipher,utility
License-File: LICENSE
Requires-Dist: pyspellchecker
